<?xml version="1.0" encoding="ISO-8859-1"?>
<forsendelse xmlns="http://kartverket.no/grunnbok/wsapi/v2/domain/innsending">
    <forsendelsesreferanse>2</forsendelsesreferanse>
    <usignertMelding>
        <dokumenter>
            <dokument>
                <dokumentreferanse>1</dokumentreferanse>
                <rettsstiftelser>
                    <annenHeftelse>
                        <rettsstiftelsesreferanse>annen.heftelse</rettsstiftelsesreferanse>
                        <rettsstiftelsestype>
                            <kodeverdi>AH_URK</kodeverdi>
                            <navn>REGISTERENHETEN KAN IKKE DISPONERES OVER UTEN SAMTYKKE FRA RETTIGHETSHAVER</navn>
                        </rettsstiftelsestype>
                        <rettighetshavere>
                            <person>
                                <navn>EIENDOMSMEGLER 1 OSLO AS</navn>
                                <identifikasjonsnummer>976756673</identifikasjonsnummer>
                            </person>
                        </rettighetshavere>
                        <realkobletTil>
                            <registerenhetsrett>
                                <registerenhetsrettstype>
                                    <kodeverdi>E</kodeverdi>
                                    <navn>Eiendomsrett</navn>
                                </registerenhetsrettstype>
                                <registerenhet>
                                    <matrikkelenhet>
                                        <kommunenummer>0301</kommunenummer>
                                        <kommunenavn>OSLO</kommunenavn>
                                        <gaardsnummer>82</gaardsnummer>
                                        <bruksnummer>2</bruksnummer>
                                        <festenummer>0</festenummer>
                                        <seksjonsnummer>0</seksjonsnummer>
                                    </matrikkelenhet>
                                </registerenhet>
                            </registerenhetsrett>
                        </realkobletTil>
                        <hefterI>
                            <delAvRegisterenhetsrett>
                                <registerenhetsrett>
                                    <registerenhetsrettstype>
                                        <kodeverdi>E</kodeverdi>
                                        <navn>Eiendomsrett</navn>
                                    </registerenhetsrettstype>
                                    <registerenhet>
                                        <matrikkelenhet>
                                            <kommunenummer>0301</kommunenummer>
                                            <kommunenavn>OSLO</kommunenavn>
                                            <gaardsnummer>82</gaardsnummer>
                                            <bruksnummer>1</bruksnummer>
                                            <festenummer>0</festenummer>
                                            <seksjonsnummer>0</seksjonsnummer>
                                        </matrikkelenhet>
                                    </registerenhet>
                                </registerenhetsrett>
                                <begrensetTil>
                                    <registerenhetsrettsandel>
                                        <teller>1</teller>
                                        <nevner>2</nevner>
                                        <rettighetshaver>
                                            <navn>Ola Nordmann</navn>
                                            <identifikasjonsnummer>15048049722</identifikasjonsnummer>
                                        </rettighetshaver>
                                    </registerenhetsrettsandel>
                                </begrensetTil>
                            </delAvRegisterenhetsrett>
                        </hefterI>
                    </annenHeftelse>
                </rettsstiftelser>
            </dokument>
        </dokumenter>
        <foelgebrev>
            <innsender>
                <identifikasjonsnummer>911044110</identifikasjonsnummer>
            </innsender>
            <dokumentrekkefoelge>
                <referanse>
                    <gjelderDokumentreferanse>1</gjelderDokumentreferanse>
                </referanse>
            </dokumentrekkefoelge>
        </foelgebrev>
    </usignertMelding>
    <ikkeDigitaleSignaturer>
        <signatur>
            <gjelderDokumentreferanse>1</gjelderDokumentreferanse>
            <personidentifikasjonsnummer>15048049722</personidentifikasjonsnummer>
        </signatur>
    </ikkeDigitaleSignaturer>
</forsendelse>